dynamask/__init__.py
dynamask/version.py
dynamask/attribution/mask.py
dynamask/attribution/mask_group.py
dynamask/attribution/perturbation.py
dynamask/baselines/explainers.py
dynamask/experiments/mimic.py
dynamask/experiments/rare_feature.py
dynamask/experiments/rare_time.py
dynamask/experiments/state.py
dynamask/experiments/results/mimic/plot_benchmarks.py
dynamask/experiments/results/rare_feature/get_results.py
dynamask/experiments/results/rare_time/get_results.py
dynamask/experiments/results/state/get_results.py
dynamask/fit/TSX/experiments.py
dynamask/fit/TSX/explainers.py
dynamask/fit/TSX/generator.py
dynamask/fit/TSX/main.py
dynamask/fit/TSX/models.py
dynamask/fit/TSX/utils.py
dynamask/fit/data_generator/data_preprocess.py
dynamask/fit/data_generator/icu_mortality.py
dynamask/fit/data_generator/state_data.py
dynamask/fit/evaluation/baselines.py
dynamask/models/models.py
dynamask/utils/losses.py
dynamask/utils/metrics.py
dynamask/utils/tensor_manipulation.py
dynamask-0.0.1.dist-info/LICENSE
dynamask-0.0.1.dist-info/METADATA
dynamask-0.0.1.dist-info/WHEEL
dynamask-0.0.1.dist-info/top_level.txt
dynamask-0.0.1.dist-info/RECORD
