Metadata-Version: 2.1
Name: dynamask
Version: 0.0.1
Summary: Dynamask - Explaining Time Series Predictions with Dynamic Masks
Home-page: https://www.vanderschaar-lab.com/
Author: Jonathan Crabbé
Author-email: jc2133@cam.ac.uk
License: MIT
Platform: any
Classifier: Programming Language :: Python :: 3
Classifier: Topic :: Scientific/Engineering :: Artificial Intelligence
Classifier: Intended Audience :: Science/Research
Classifier: License :: OSI Approved :: MIT License
Classifier: Operating System :: OS Independent
Requires-Dist: captum (>=0.3.0)
Requires-Dist: lime (>=0.2.0.1)
Requires-Dist: numpy (>=1.19.2)
Requires-Dist: pandas (>=1.1.3)
Requires-Dist: psycopg2-binary
Requires-Dist: scikit-learn (>=0.23.2)
Requires-Dist: scipy (>=1.5.2)
Requires-Dist: seaborn (>=0.11.0)
Requires-Dist: statsmodels (>=0.12.1)
Requires-Dist: torch (>=1.7.1)
Requires-Dist: tqdm (>=4.61.0)
Requires-Dist: importlib-metadata ; python_version < "3.8"
Provides-Extra: testing
Requires-Dist: pre-commit ; extra == 'testing'
Requires-Dist: setuptools ; extra == 'testing'
Requires-Dist: pytest ; extra == 'testing'
Requires-Dist: pytest-cov ; extra == 'testing'
Requires-Dist: bandit ; extra == 'testing'
Requires-Dist: jupyter ; extra == 'testing'
Requires-Dist: notebook ; extra == 'testing'
